README.md
setup.py
mario_64_super_star_battle.egg-info/PKG-INFO
mario_64_super_star_battle.egg-info/SOURCES.txt
mario_64_super_star_battle.egg-info/dependency_links.txt
mario_64_super_star_battle.egg-info/entry_points.txt
mario_64_super_star_battle.egg-info/requires.txt
mario_64_super_star_battle.egg-info/top_level.txt
mario_battle/__init__.py
mario_battle/battle_class.py
mario_battle/constants.py
mario_battle/io.py
mario_battle/main.py
mario_battle/markdown_summary.py
mario_battle/version.py