Metadata-Version: 2.1
Name: mario-64-super-star-battle
Version: 0.0.3
Summary: The ultimate competition between Mario 64 superstars
Home-page: https://github.com/mwiens91/mario-64-super-star-battle
Author: Branko Bajcetic, Matt Wiens
Author-email: bajcetic.branko@gmail.com, mwiens91@gmail.com
License: BSD 3-clause "New" or "Revised License"
Platform: UNKNOWN
Classifier: Intended Audience :: End Users/Desktop
Classifier: License :: OSI Approved :: BSD License
Classifier: Natural Language :: English
Classifier: Programming Language :: Python :: 3 :: Only
Requires-Python: >=3
